README.txt
setup.py
collective/__init__.py
collective.migrator.egg-info/PKG-INFO
collective.migrator.egg-info/SOURCES.txt
collective.migrator.egg-info/dependency_links.txt
collective.migrator.egg-info/entry_points.txt
collective.migrator.egg-info/namespace_packages.txt
collective.migrator.egg-info/not-zip-safe
collective.migrator.egg-info/requires.txt
collective.migrator.egg-info/top_level.txt
collective/migrator/__init__.py
collective/migrator/buildout.cfg
collective/migrator/migrator.py
collective/migrator/recipes/__init__.py
collective/migrator/recipes/migrator.py
collective/migrator/recipes/utils.py
collective/migrator/scripts/__init__.py
collective/migrator/scripts/actions.py
collective/migrator/scripts/content.py
collective/migrator/scripts/memberdata.py
collective/migrator/scripts/mod_time.py
collective/migrator/scripts/props.py
collective/migrator/scripts/related_items.py
collective/migrator/scripts/site_config.py
collective/migrator/scripts/sitemap.py
collective/migrator/templates/__init__.py
collective/migrator/templates/eggs.cfg
collective/migrator/templates/instance.cfg
collective/migrator/templates/migrate_frontpage.cfg
collective/migrator/templates/migrate_junk.cfg
collective/migrator/templates/migrate_mem.cfg
collective/migrator/templates/migrate_misc.cfg
collective/migrator/templates/migrate_props.cfg
collective/migrator/templates/migrate_users.cfg
collective/migrator/tests/__init__.py
collective/migrator/tests/testUtils.py
collective/migrator/tests/testUtils2.py
docs/HISTORY.txt