Metadata-Version: 1.0
Name: collective.migrator
Version: 1.8
Summary: Tool and buildout recipes for zope/plone content migration
Home-page: http://plone.org/products/collective.migrator
Author: Suresh V
Author-email: suresh@grafware.com
License: GPL
Keywords: buildout recipe zope plone content migration
Platform: UNKNOWN
Classifier: Programming Language :: Python
Classifier: Framework :: Buildout
